atapibasiclib/__init__.py
atapibasiclib/apirequest.py
atapibasiclib/apitestbasic.py
atapibasiclib/getfromxls.py
atapibasiclib/jsoncompare.py
atapibasiclib/mysqllib.py
cov/__init__.py
cov/cau.py
cov/test_cover.py
api_basic_lib-1.0.dist-info/METADATA
api_basic_lib-1.0.dist-info/WHEEL
api_basic_lib-1.0.dist-info/top_level.txt
api_basic_lib-1.0.dist-info/RECORD
